jordan_form/__init__.py
jordan_form/__main__.py
jordan_form/_jordan_chain.py
jordan_form/_multiplicity.py
jordan_form/cli.py
jordan_form/plot.py
jordan_form/py.typed
jordan_form-1.0.0.dist-info/licenses/LICENSE
jordan_form-1.0.0.dist-info/METADATA
jordan_form-1.0.0.dist-info/WHEEL
jordan_form-1.0.0.dist-info/entry_points.txt
jordan_form-1.0.0.dist-info/top_level.txt
jordan_form-1.0.0.dist-info/RECORD
