Metadata-Version: 2.4
Name: jordan-form
Version: 1.0.0
Summary: Compute jordan canonical (normal) form of (nonlinear / generalized) eigenvalue problem
Author-email: 34j <34j.95a2p@simplelogin.com>
License: MIT
Project-URL: Bug Tracker, https://github.com/34j/jordan-form/issues
Project-URL: Changelog, https://github.com/34j/jordan-form/blob/main/CHANGELOG.md
Project-URL: documentation, https://jordan-form.readthedocs.io
Project-URL: repository, https://github.com/34j/jordan-form
Classifier: Development Status :: 2 - Pre-Alpha
Classifier: Intended Audience :: Developers
Classifier: Natural Language :: English
Classifier: Operating System :: OS Independent
Classifier: Programming Language :: Python :: 3.9
Classifier: Programming Language :: Python :: 3.10
Classifier: Programming Language :: Python :: 3.11
Classifier: Programming Language :: Python :: 3.12
Classifier: Programming Language :: Python :: 3.13
Classifier: Topic :: Software Development :: Libraries
Requires-Python: >=3.10
License-File: LICENSE
Requires-Dist: attrs>=25.3.0
Requires-Dist: numpy>=2.0.2
Requires-Dist: rich>=10
Requires-Dist: scipy>=1.13.1
Requires-Dist: sympy>=1.14.0
Requires-Dist: typer<1,>=0.15
Provides-Extra: matplotlib
Requires-Dist: matplotlib>=3.9.4; extra == "matplotlib"
Dynamic: license-file
